timescale/.DS_Store
timescale/__init__.py
timescale/db/.DS_Store
timescale/db/__init__.py
timescale/db/backends/.DS_Store
timescale/db/backends/__init__.py
timescale/db/backends/postgis/__init__.py
timescale/db/backends/postgis/base.py
timescale/db/backends/postgis/base_impl.py
timescale/db/backends/postgis/schema.py
timescale/db/backends/postgresql/__init__.py
timescale/db/backends/postgresql/base.py
timescale/db/backends/postgresql/base_impl.py
timescale/db/backends/postgresql/schema.py
timescale/db/models/__init__.py
timescale/db/models/aggregates.py
timescale/db/models/expressions.py
timescale/db/models/fields.py
timescale/db/models/managers.py
timescale/db/models/models.py
timescale/db/models/querysets.py
timescale/tests/__init__.py
timescale/tests/conftest.py
timescale/tests/factories.py
timescale/tests/test_models.py
django_timescaledb-0.2.12.dist-info/LICENSE
django_timescaledb-0.2.12.dist-info/METADATA
django_timescaledb-0.2.12.dist-info/WHEEL
django_timescaledb-0.2.12.dist-info/top_level.txt
django_timescaledb-0.2.12.dist-info/RECORD
